printcleaner/__init__.py
printcleaner/clean.py
printcleaner/transformer.py
printcleaner-0.1.6.dist-info/entry_points.txt
printcleaner-0.1.6.dist-info/LICENSE
printcleaner-0.1.6.dist-info/WHEEL
printcleaner-0.1.6.dist-info/METADATA
printcleaner-0.1.6.dist-info/RECORD
